{
  "lecture_topic": "Lists in Python",
  "lecture_summary": "The lecture covers the fundamental concepts of lists in Python, including their mutability, indexing, slicing, and various list operations such as append, extend, pop, and remove. It also briefly touches on biology topics like mitosis and cell division.",
  "concepts": [
    {
      "id": "concept_1",
      "name": "List",
      "aliases": [
        "data type"
      ],
      "description": "A list is a data type in Python that can store different types of elements and is mutable, allowing modifications, additions, and deletions.",
      "type": "core",
      "explanation_method": "Formal definition and examples",
      "key_points": [
        "Lists are defined using square brackets.",
        "Lists can store various data types such as integers, floats, strings, booleans, and complex numbers."
      ],
      "complexity_note": "N/A"
    },
    {
      "id": "concept_2",
      "name": "Mutability",
      "aliases": [
        "mutable data type"
      ],
      "description": "Lists are mutable, meaning their contents can be changed after creation.",
      "type": "core",
      "explanation_method": "Explanation through examples",
      "key_points": [
        "Allows modification, addition, and deletion of elements.",
        "Contrasts with immutable data types."
      ],
      "complexity_note": "N/A"
    },
    {
      "id": "concept_3",
      "name": "Indexing",
      "aliases": [
        "forward indexing",
        "negative indexing"
      ],
      "description": "Indexing allows accessing elements in a list by their position, using zero-based forward indexing or negative indexing from the end.",
      "type": "core",
      "explanation_method": "Analogy and examples",
      "key_points": [
        "Forward indexing starts at 0.",
        "Negative indexing starts at -1."
      ],
      "complexity_note": "N/A"
    },
    {
      "id": "concept_4",
      "name": "Slicing",
      "aliases": [
        "list slicing"
      ],
      "description": "Slicing involves cutting a list into parts by specifying start, stop, and skip values.",
      "type": "core",
      "explanation_method": "Example",
      "key_points": [
        "Allows extraction of sublists.",
        "Involves start, stop, and step parameters."
      ],
      "complexity_note": "N/A"
    },
    {
      "id": "concept_5",
      "name": "CRUD Operations",
      "aliases": [
        "Create, Read, Update, Delete"
      ],
      "description": "CRUD operations refer to the basic functions of persistent storage, applicable to list operations.",
      "type": "supporting",
      "explanation_method": "Explanation through list methods",
      "key_points": [
        "Create: Adding elements.",
        "Read: Accessing elements.",
        "Update: Modifying elements.",
        "Delete: Removing elements."
      ],
      "complexity_note": "N/A"
    },
    {
      "id": "concept_6",
      "name": "Append Method",
      "aliases": [
        "append"
      ],
      "description": "The append method adds an element to the end of a list.",
      "type": "supporting",
      "explanation_method": "Example",
      "key_points": [
        "Adds a single element.",
        "Changes the list in place."
      ],
      "complexity_note": "Time complexity: O(1)"
    },
    {
      "id": "concept_7",
      "name": "Extend Method",
      "aliases": [
        "extend"
      ],
      "description": "The extend method adds multiple elements to the end of a list.",
      "type": "supporting",
      "explanation_method": "Example",
      "key_points": [
        "Adds elements from another iterable.",
        "Changes the list in place."
      ],
      "complexity_note": "Time complexity: O(k), where k is the number of elements added."
    },
    {
      "id": "concept_8",
      "name": "Pop Method",
      "aliases": [
        "pop"
      ],
      "description": "The pop method removes an element from a list by index and returns it.",
      "type": "supporting",
      "explanation_method": "Example",
      "key_points": [
        "Removes and returns the element at the specified index.",
        "Default index is -1 (last element)."
      ],
      "complexity_note": "Time complexity: O(n) due to list re-indexing."
    },
    {
      "id": "concept_9",
      "name": "Remove Method",
      "aliases": [
        "remove"
      ],
      "description": "The remove method deletes the first occurrence of a specified element from a list.",
      "type": "supporting",
      "explanation_method": "Example",
      "key_points": [
        "Removes the first matching element.",
        "Raises ValueError if the element is not found."
      ],
      "complexity_note": "Time complexity: O(n)"
    },
    {
      "id": "concept_10",
      "name": "For Loop",
      "aliases": [
        "iteration"
      ],
      "description": "A for loop is used to iterate over each element in a list, allowing operations to be performed on each element.",
      "type": "supporting",
      "explanation_method": "Example",
      "key_points": [
        "Iterates over list elements.",
        "Useful for processing each element individually."
      ],
      "complexity_note": "Time complexity: O(n)"
    }
  ],
  "teaching_flow": [
    "concept_1 -> concept_2",
    "concept_2 -> concept_3",
    "concept_3 -> concept_4",
    "concept_4 -> concept_5",
    "concept_5 -> concept_6",
    "concept_6 -> concept_7",
    "concept_7 -> concept_8",
    "concept_8 -> concept_9",
    "concept_9 -> concept_10"
  ],
  "analogies_used": [
    {
      "concept": "concept_3",
      "analogy": "Indexing is like having an index in a book."
    }
  ]
}